ivory-0.5.2.dist-info/METADATA
ivory-0.5.2.dist-info/WHEEL
ivory/optimize.py
ivory/typing.py
ivory/__init__.py
ivory/ivory.pyd
ivory-0.5.2.dist-info/RECORD
